{"description":"","tags":{"since":[{"description":"4.0.0","title":"since"}]},"displayName":"Navigate","props":[{"name":"axis","type":{"name":"string"}},{"name":"disabled","type":{"name":"boolean"}},{"name":"element","type":{"name":"string"},"defaultValue":{"value":"\"div\""}},{"name":"select","type":{"name":"string"},"defaultValue":{"value":"\":where(button, a):not(:disabled)\""}}],"events":[{"name":"next"},{"name":"prev"}],"slots":[{"name":"default"}],"component":"k-navigate","sourceFile":"src/components/Navigation/Navigate.vue"}