{"displayName":"StructureForm","description":"","tags":{},"props":[{"name":"fields","description":"Form fields","type":{"name":"object"}},{"name":"index","description":"Index of current model/row","type":{"name":"number|string"}},{"name":"total","description":"Total number of rows in field","type":{"name":"number"}},{"name":"value","type":{"name":"object"}}],"events":[{"name":"close"},{"name":"paginate"},{"name":"discard"},{"name":"input","type":{"names":["undefined"]}},{"name":"submit"}],"component":"k-structure-form","sourceFile":"src/components/Forms/Structure/StructureForm.vue"}