{"description":"Toolbar for `k-textarea-input`","tags":{"since":[{"description":"4.0.0","title":"since"}],"unstable":[{"description":true,"title":"unstable"}]},"displayName":"TextareaToolbar","props":[{"name":"buttons","type":{"name":"array|boolean"},"defaultValue":{"value":"true"}},{"name":"uploads","description":"Whether the toolbar's file upload button shows a dropdown with\nselect and upload options or emits event directly","type":{"name":"boolean|object|array"}}],"events":[{"name":"command","type":{"names":["undefined"]},"properties":[{"type":{"names":["undefined"]},"name":"<anonymous1>"}]}],"component":"k-textarea-toolbar","sourceFile":"src/components/Forms/Toolbar/TextareaToolbar.vue"}